lab3/halfAdder.v
module halfAdder(
    input A, B,
    output S, Cout
);
xor(S, A, B);
and(Cout, A, B);

endmodule

lab3/fullAdder.v
module fullAdder(
    input A, B, Cin,
    output S, Cout
);


halfAdder h0(
    A,
    B,
    AxB,
    AnB2
);
halfAdder h1(
    A,
    Cin,
    S,
    AnB1
);

or(Cout, AnB1, AnB2);

endmodule

lab3/fullAddertb.v
module fullAddertb();
reg r1,r2,r3;
wire w1,w2;

fullAdder uut(
    .A(r1),
    .B(r2),
    .Cin(r3),
    .S(w1),
    .Cout(w2)
);

initial begin
    $dumpfile("fdmp.vcd");
    $dumpvars;
    r1= 1'b0;   r2= 1'b0;   r3= 1'b0; #10;
    r1= 1'b0;   r2= 1'b0;   r3= 1'b1; #10;
    r1= 1'b0;   r2= 1'b1;   r3= 1'b0; #10;
    r1= 1'b0;   r2= 1'b1;   r3= 1'b1; #10;
    r1= 1'b1;   r2= 1'b0;   r3= 1'b0; #10;
    r1= 1'b1;   r2= 1'b0;   r3= 1'b1; #10;
    r1= 1'b1;   r2= 1'b1;   r3= 1'b0; #10;
    r1= 1'b1;   r2= 1'b1;   r3= 1'b1; #10;

    $display(w1);
    $display(w2);
    $finish;

end

endmodule

lab3/fdmp.vcd
$date
	Sat Dec 14 00:44:17 2024
$end
$version
	Icarus Verilog
$end
$timescale
	1s
$end
$scope module fullAddertb $end
$var wire 1 ! w2 $end
$var wire 1 " w1 $end
$var reg 1 # r1 $end
$var reg 1 $ r2 $end
$var reg 1 % r3 $end
$scope module uut $end
$var wire 1 # A $end
$var wire 1 $ B $end
$var wire 1 % Cin $end
$var wire 1 ! Cout $end
$var wire 1 " S $end
$var wire 1 & AxB $end
$var wire 1 ' AnB2 $end
$var wire 1 ( AnB1 $end
$scope module h0 $end
$var wire 1 # A $end
$var wire 1 $ B $end
$var wire 1 ' Cout $end
$var wire 1 & S $end
$upscope $end
$scope module h1 $end
$var wire 1 # A $end
$var wire 1 % B $end
$var wire 1 ( Cout $end
$var wire 1 " S $end
$upscope $end
$upscope $end
$upscope $end
$enddefinitions $end
$comment Show the parameter values. $end
$dumpall
$end
#0
$dumpvars
0(
0'
0&
0%
0$
0#
0"
0!
$end
#10
1"
1%
#20
0"
1&
0%
1$
#30
1"
1%
#40
0%
0$
1#
#50
1!
0"
1(
1%
#60
1"
0(
0&
1'
0%
1$
#70
0"
1(
1%
